smmo/__init__.py
smmo/data.py
smmo/smatrix.py
smmo-0.0.4.dist-info/METADATA
smmo-0.0.4.dist-info/WHEEL
smmo-0.0.4.dist-info/top_level.txt
smmo-0.0.4.dist-info/RECORD
