Metadata-Version: 2.1
Name: smmo
Version: 0.0.4
Summary: Scattering-Matrix method for multilayer optics
Home-page: https://github.com/phykn/smmo
Author: Kwangnam Yu
Author-email: phykn.kr@gmail.com
License: UNKNOWN
Platform: UNKNOWN
Classifier: Programming Language :: Python :: 3
Classifier: License :: OSI Approved :: MIT License
Classifier: Operating System :: OS Independent
Requires-Python: >=3.6
Requires-Dist: numpy
